atprun/__init__.py
atprun/app_main.py
atprun/app_script.py
atprun/cli.py
atprun-0.1.11.dist-info/licenses/LICENSE
atprun-0.1.11.dist-info/METADATA
atprun-0.1.11.dist-info/WHEEL
atprun-0.1.11.dist-info/entry_points.txt
atprun-0.1.11.dist-info/top_level.txt
atprun-0.1.11.dist-info/RECORD
