Metadata-Version: 2.4
Name: atprun
Version: 0.1.11
Summary: Run commands, scripts and import environmental variables
Author-email: Andraz Polak <andrazpolak@gmail.com>
Project-URL: homepage, https://github.com/atp-things/atp-run
Project-URL: repository, https://github.com/atp-things/atp-run
Project-URL: PyPI, https://pypi.org/project/atprun/
Classifier: Programming Language :: Python
Classifier: Programming Language :: Python :: 3
Classifier: Operating System :: OS Independent
Requires-Python: >=3.11
License-File: LICENSE
Requires-Dist: atptools>=0.1.31
Requires-Dist: pyyaml>=6.0.2
Requires-Dist: rich>=14.1.0
Requires-Dist: typer>=0.17.3
Requires-Dist: types-pyyaml>=6.0.12.20250809
Dynamic: license-file
